{"cameraMode":{"drawMode":0,"name":"Shaded","section":"Shading Mode"},"sceneLighting":true,"audioPlay":false,"sceneViewState":{"showFog":true,"showMaterialUpdate":false,"showSkybox":true,"showFlares":true,"showImageEffects":true,"showParticleSystems":true},"in2DMode":false,"pivot":{"x":9939.6767578125,"y":9984.451171875,"z":10068.9326171875},"rotation":{"x":-0.11905217170715332,"y":0.49950700998306277,"z":-0.06953065097332001,"w":-0.8552697896957398},"size":86.40328979492188,"orthographic":false}